otobo_znuny/__init__.py
otobo_znuny/mappers.py
otobo_znuny/clients/__init__.py
otobo_znuny/clients/otobo_client.py
otobo_znuny/domain_models/__init__.py
otobo_znuny/domain_models/basic_auth_model.py
otobo_znuny/domain_models/otobo_client_config.py
otobo_znuny/domain_models/ticket_models.py
otobo_znuny/domain_models/ticket_operation.py
otobo_znuny/models/__init__.py
otobo_znuny/models/base_models.py
otobo_znuny/models/request_models.py
otobo_znuny/models/response_models.py
otobo_znuny/models/ticket_models.py
otobo_znuny/scripts/__init__.py
otobo_znuny/scripts/cli_interface.py
otobo_znuny/scripts/getting_started.py
otobo_znuny/scripts/setup_webservices.py
otobo_znuny/scripts/webservice_util.py
otobo_znuny/util/__init__.py
otobo_znuny/util/otobo_errors.py
otobo_znuny/util/safe_base_model.py
otobo_znuny/util/webservice_config.py
otobo_znuny-1.4.1.dist-info/METADATA
otobo_znuny-1.4.1.dist-info/WHEEL
otobo_znuny-1.4.1.dist-info/top_level.txt
otobo_znuny-1.4.1.dist-info/RECORD
