Metadata-Version: 2.4
Name: otobo_znuny
Version: 1.4.1
Summary: Python client library for the OTOBO / Znuny REST API
Author-email: Tobias Bück <tab@softoft.de>
License: MIT
Project-URL: homepage, https://otobo-docs.softoft.de/administration/automation/rest-api
Project-URL: documentation, https://otobo-docs.softoft.de/administration/automation/rest-api
Classifier: Development Status :: 5 - Production/Stable
Classifier: Programming Language :: Python :: 3
Classifier: Programming Language :: Python :: 3.11
Classifier: Programming Language :: Python :: 3.12
Classifier: Programming Language :: Python :: 3.13
Classifier: License :: OSI Approved :: MIT License
Classifier: Operating System :: OS Independent
Classifier: Topic :: Software Development :: Libraries :: Python Modules
Classifier: Framework :: AsyncIO
Requires-Python: >=3.11
Requires-Dist: httpx<0.29,>=0.27
Requires-Dist: pydantic<3,>=2.11.3
Requires-Dist: python-dotenv>=1.0.1
Requires-Dist: pyyaml>=6.0.2
Requires-Dist: requests<3,>=2.28
Requires-Dist: typer<0.20,>=0.13.1
Provides-Extra: dev
Requires-Dist: pytest>=8.3.5; extra == "dev"
Requires-Dist: pytest-asyncio>=0.24.0; extra == "dev"
Requires-Dist: mariadb>=1.1.13; extra == "dev"
Requires-Dist: mypy>=1.18.2; extra == "dev"
Requires-Dist: ruff>=0.13.1; extra == "dev"
Requires-Dist: types-pyyaml>=6.0.12.20250915; extra == "dev"
Requires-Dist: types-requests>=2.32.4.20250913; extra == "dev"
